{"cameraMode":{"drawMode":0,"name":"Shaded","section":"Shading Mode"},"sceneLighting":true,"audioPlay":false,"sceneViewState":{"m_AlwaysRefresh":false,"showFog":true,"showSkybox":true,"showFlares":true,"showImageEffects":true,"showParticleSystems":true,"showVisualEffectGraphs":true,"m_FxEnabled":true},"in2DMode":false,"pivot":{"x":-7.023761749267578,"y":2.469890594482422,"z":35.58045959472656},"rotation":{"x":0.0,"y":0.7071068286895752,"z":0.0,"w":0.7071068286895752},"size":45.75171661376953,"orthographic":false}